README.txt
setup.py
cifilter/__init__.py
cifilter/cifilter.py
cifilter.egg-info/PKG-INFO
cifilter.egg-info/SOURCES.txt
cifilter.egg-info/dependency_links.txt
cifilter.egg-info/top_level.txt
scripts/cifilter