Metadata-Version: 1.0
Name: cifilter
Version: 0.4.2
Summary: CoreImage command line tool
Home-page: http://github.com/schwa/cifilter/
Author: Jonathan Wight
Author-email: jwight@mac.com
License: BSD License
Platform: Mac OS X
Classifier: Development Status :: 3 - Alpha
Classifier: Environment :: MacOS X :: Cocoa
Classifier: Intended Audience :: Developers
Classifier: License :: OSI Approved :: BSD License
Classifier: Operating System :: MacOS :: MacOS X
Classifier: Programming Language :: Objective C
Classifier: Topic :: Multimedia :: Graphics
Classifier: Topic :: Multimedia :: Graphics :: Editors :: Raster-Based
Classifier: Topic :: Software Development
